parameterize_jobs/__init__.py
parameterize_jobs/_compat.py
parameterize_jobs/_utils.py
parameterize_jobs/_version.py
parameterize_jobs/parameterize_jobs.py
parameterize_jobs-0.2.0.dist-info/METADATA
parameterize_jobs-0.2.0.dist-info/WHEEL
parameterize_jobs-0.2.0.dist-info/licenses/LICENSE
parameterize_jobs-0.2.0.dist-info/RECORD
