Metadata-Version: 2.1
Name: parameterize_jobs
Version: 0.2.0
Summary: Concisely and clearly create large, parameterized, mapped job specifications
Project-URL: Homepage, https://github.com/ClimateImpactLab/parameterize_jobs
Project-URL: Bug Tracker, https://github.com/ClimateImpactLab/parameterize_jobs/issues
Author-email: Michael Delgado <delgado.michaelt@gmail.com>
License-File: LICENSE
Classifier: Intended Audience :: Developers
Classifier: License :: OSI Approved :: MIT License
Classifier: Natural Language :: English
Classifier: Programming Language :: Python :: 3
Requires-Python: >=3.9
Provides-Extra: docs
Requires-Dist: ipython; extra == 'docs'
Requires-Dist: sphinx; extra == 'docs'
Requires-Dist: sphinx-rtd-theme; extra == 'docs'
Provides-Extra: test
Requires-Dist: pytest; extra == 'test'
Requires-Dist: pytest-cov; extra == 'test'
Requires-Dist: ruff; extra == 'test'
